ytps/__init__.py
ytps/__main__.py
ytps-1.2.2.dist-info/LICENSE
ytps-1.2.2.dist-info/METADATA
ytps-1.2.2.dist-info/WHEEL
ytps-1.2.2.dist-info/entry_points.txt
ytps-1.2.2.dist-info/top_level.txt
ytps-1.2.2.dist-info/RECORD
