Metadata-Version: 2.1
Name: ytps
Version: 1.2.2
Summary: Youtube Search in the CLI - Improved
Home-page: https://github.com/newtoallofthis123/ytps
Author: NoobScience
Author-email: noobscience123@gmail.com
License: MIT
Project-URL: Author WebSite, https://newtoallofthis123.github.io/About
Project-URL: Bug Tracker, https://github.com/newtoallofthis123/ytps/issues
Classifier: License :: OSI Approved :: MIT License
Classifier: Programming Language :: Python :: 3
Classifier: Programming Language :: Python :: 3.7
Requires-Python: >=3.6
License-File: LICENSE
Requires-Dist: rich
Requires-Dist: youtube-search
Requires-Dist: youtube-search-python
Requires-Dist: youtube-dl
Requires-Dist: speedtest-cli
